MASSiveChem/MASSiveChem.py
MASSiveChem/__init__.py
massivechem-6.0.dist-info/METADATA
massivechem-6.0.dist-info/WHEEL
massivechem-6.0.dist-info/licenses/LICENSE.txt
massivechem-6.0.dist-info/RECORD
