Metadata-Version: 2.3
Name: MASSIVEChem
Version: 6.0
Summary: MASSIVEChem is a pip-installable package for analytical chemistry. It simulates molecule mass spectra and graphically displays them. It includes tools like a functional group finder and unsaturation calculator to aid chemical analysis.
Project-URL: Homepage, https://github.com/ThomasCsson/MASSIVEChem.git
Project-URL: GitHub_Thomas_Christiansson, https://github.com/ThomasCsson
Project-URL: GitHub_Igor_Gonteri, https://github.com/igorgonteri
Project-URL: GitHub_Arthur_Humery, https://github.com/Arthurhmy
Author-email: Thomas Viking Christiansson <thomas.christiansson@epfl.ch>, Igor Gonteri <igor.gonteri@epfl.ch>, Arthur Humery <arthur.humery@epfl.ch>
License-Expression: MIT
License-File: LICENSE.txt
Keywords: Mass spectroscopy,chemical-engineering,chemical-property-prediction,cheminformatics,chemistry,chemistry-lab,functional group,spectrometry,spectroscopy,unsaturation
Classifier: Development Status :: 4 - Beta
Classifier: License :: OSI Approved :: MIT License
Classifier: Operating System :: OS Independent
Classifier: Programming Language :: Python :: 3
Requires-Python: >=3.8
Requires-Dist: bokeh
Requires-Dist: panel
Requires-Dist: rdkit
